algoind/__init__.py
algoind/indicators.py
algoind-0.0.3.dist-info/METADATA
algoind-0.0.3.dist-info/WHEEL
algoind-0.0.3.dist-info/licenses/LICENSE.txt
algoind-0.0.3.dist-info/RECORD
