Metadata-Version: 2.1
Name: algoind
Version: 0.0.3
Summary: A collection of technical indicators for backtesting and for implementing trading strategies in Python3.
Project-URL: Homepage, https://github.com/matteoincremona/techind
Project-URL: Bug Tracker, https://github.com/matteoincremona/techind/issues
Author-email: Matteo Incremona <matteoincremona82@gmail.com>
License: MIT License
License-File: LICENSE.txt
Keywords: backtesting,finance,indicator,pandas,quantitative,trading
Classifier: License :: OSI Approved :: MIT License
Classifier: Operating System :: OS Independent
Classifier: Programming Language :: Python :: 3
Requires-Python: >=3.7
